{
  "ids": {
    "User": 1,
    "AccessToken": 1,
    "ACL": 1,
    "RoleMapping": 1,
    "Role": 1,
    "AppUser": 6,
    "App": 5,
    "Comment": 2
  },
  "models": {
    "User": {},
    "AccessToken": {},
    "ACL": {},
    "RoleMapping": {},
    "Role": {},
    "AppUser": {
      "1": "{\"login\":\"admin\",\"pass\":\"1488\",\"role\":0,\"name\":\"Администратор\",\"lastsession\":\"2016-09-10T20:33:48.362Z\",\"id\":1}",
      "2": "{\"login\":\"executor\",\"pass\":\"3222\",\"role\":1,\"name\":\"Исполнитель №1\",\"lastsession\":\"2016-09-10T18:19:10.197Z\",\"id\":2}",
      "3": "{\"login\":\"client\",\"pass\":\"3222\",\"role\":2,\"name\":\"Клиент №1\",\"lastsession\":\"2016-09-10T18:31:54.198Z\",\"id\":3}",
      "5": "{\"login\":\"client2\",\"pass\":\"3222\",\"role\":2,\"name\":\"Клиент №2\",\"lastsession\":\"2016-09-10T20:18:19.045Z\",\"id\":5}"
    },
    "App": {
      "3": "{\"Name\":\"Test\",\"Date\":\"2016-09-10T23:17:00.000Z\",\"Client\":\"client\",\"ClientName\":\"Клиент №1\",\"Executor\":\"executor\",\"ExecutorName\":\"Исполнитель №1\",\"Discription\":\"Test Test Test\",\"Priority\":0,\"Estimated\":\"2016-10-10T23:17:00.000Z\",\"Deadline\":\"2016-10-10T23:17:00.000Z\",\"Progress\":44,\"id\":3}",
      "4": "{\"Name\":\"Тест\",\"Date\":\"2016-09-10T23:18:00.000Z\",\"Client\":\"client2\",\"ClientName\":\"Клиент №2\",\"Executor\":\"null\",\"ExecutorName\":\"Нет\",\"Discription\":\"Тест Тест Тест\",\"Priority\":2,\"Estimated\":\"2016-10-10T23:18:00.000Z\",\"Deadline\":\"2016-10-10T23:18:00.000Z\",\"Progress\":14,\"id\":4}"
    },
    "Comment": {
      "1": "{\"App\":1,\"User\":\"admin\",\"UserName\":\"Администратор\",\"Date\":\"2016-09-10T21:46:00.000Z\",\"Text\":\"lolololo\",\"id\":1}"
    }
  }
}